{"components_app-bar.md":"cc8d06e9","components_autocomplete.md":"1ef40977","components_alert.md":"08ebe02f","components_avatar.md":"01c91041","components_badge.md":"beb11eb1","components_breadcrumbs.md":"d7b9da80","components_bottom-sheet.md":"e77db124","components_navigation-drawer.md":"8a01d1d7","components_pagination.md":"18dcc863","components_quill-editor.md":"7a9bcf6c","components_radio-group.md":"793552c8","components_progress-bar.md":"cfa04581","components_radio.md":"64996d80","components_rating.md":"b6005f9e","components_select.md":"33044c41","components_shimmer.md":"9c2141c1","components_stepper.md":"ed1ebcfe","components_spinner.md":"b1114218","components_switch.md":"fdef9515","components_tabs.md":"45c2fa05","components_toast.md":"1f02934f","components_text.md":"b3424e37","components_card.md":"868909f8","components_data-table-pagination.md":"967b5f92","components_textarea.md":"1961576d","components_logo.md":"d796d47e","components_menus.md":"f8349c2b","components_menu.md":"3580bc51","components_checkbox.md":"65ca7487","components_tooltip.md":"c4fad580","components_file-input.md":"3e7d1b35","components_editor.md":"5c64f160","components_input.md":"5be44183","components_form-select.md":"9550a54c","components_input-range.md":"c5a264c7","components_navbar.md":"6205c804","components_modal.md":"12a03315","components_data-table.md":"6dfcd6db","components_nav-drawer.md":"2da5102e","components_button.md":"440ae13a","guide_installation.md":"d42163ab","components_multi-select.md":"46606a25","guide_changelog.md":"cfefe19e","guide_dark-mode.md":"254a9c04","guide_getting-started.md":"d607de07","guide_introduction.md":"ad57e280","guide_nuxt.md":"f52d420a","guide_starter.md":"d2862f39","index.md":"50440812","roadmap.md":"1b075ed9","guide_theme.md":"cb7e2793","themes_nuxt-admin.md":"ea6ac93f","tools_cli.md":"30e6c13d","guide_customization.md":"70927bf2","themes_nuxt-auth.md":"9bb68473","guide_migration.md":"0c81e03e","components_collapsible.md":"3c42826c","guide_vue.md":"6042a729","components_list.md":"a11bca65","components_icon.md":"b982bf3e","components_dropdown.md":"5478fc63"}
